pyposdisplay/__init__.py
pyposdisplay/pyposdisplay.py
pyposdisplay-0.0.4.dist-info/METADATA
pyposdisplay-0.0.4.dist-info/WHEEL
pyposdisplay-0.0.4.dist-info/top_level.txt
pyposdisplay-0.0.4.dist-info/RECORD
