Metadata-Version: 2.1
Name: pyposdisplay
Version: 0.0.4
Summary: Python library to support Point Of Sale displays
Home-page: https://github.com/akretion/pyposdisplay
Author: Akretion
Author-email: contact@akretion.com
License: AGPLv3+
Keywords: bixolon epson lcd display pos point of sale
Platform: UNKNOWN
Classifier: Development Status :: 3 - Alpha
Classifier: Intended Audience :: Developers
Classifier: Topic :: Software Development :: User Interfaces
Classifier: License :: OSI Approved :: GNU Affero General Public License v3
Classifier: Programming Language :: Python :: 2.7
Requires-Dist: unidecode
Requires-Dist: pyserial
Requires-Dist: pyusb
